tabular_2_text/__init__.py
tabular_2_text/converter.py
tabular_2_text-0.1.7.dist-info/LICENSE
tabular_2_text-0.1.7.dist-info/METADATA
tabular_2_text-0.1.7.dist-info/WHEEL
tabular_2_text-0.1.7.dist-info/top_level.txt
tabular_2_text-0.1.7.dist-info/RECORD
