Metadata-Version: 2.1
Name: tabular-2-text
Version: 0.1.7
Summary: Take a df or csv and convert to text
Home-page: https://github.com/sandeepmj/tabular_2_text
Author: Sandeep Junnarkar
Author-email: sjnews@gmail.com
License: UNKNOWN
Platform: UNKNOWN
Classifier: Programming Language :: Python :: 3
Classifier: License :: OSI Approved :: MIT License
Classifier: Operating System :: OS Independent
Requires-Python: >=3.7
License-File: LICENSE
Requires-Dist: numpy (>=1.21.0)
Requires-Dist: pandas (>=1.3.0)
